pyoperaciones/__init__.py
pyoperaciones/utils.py
pyoperacion_AlvaroM-0.1.dist-info/LICENSE.txt
pyoperacion_AlvaroM-0.1.dist-info/METADATA
pyoperacion_AlvaroM-0.1.dist-info/WHEEL
pyoperacion_AlvaroM-0.1.dist-info/top_level.txt
pyoperacion_AlvaroM-0.1.dist-info/RECORD
