Metadata-Version: 2.1
Name: pyoperacion-AlvaroM
Version: 0.1
Summary: A tool to perform mathematical operations.
Home-page: UNKNOWN
Author: Alvaro Moreno Matesanz
Author-email: alvaroprimi@gmail.com
License: GNU GPLv3
Keywords: pyoperaciones mathematical operations
Platform: UNKNOWN
Classifier: Development Status :: 4 - Beta
Classifier: Intended Audience :: Developers
Classifier: Topic :: Utilities
Classifier: License :: OSI Approved :: GNU General Public License v3 (GPLv3)
Classifier: Programming Language :: Python :: 3
Classifier: Operating System :: OS Independent
License-File: LICENSE.txt
